debrepo.py
mkrepo.py
rpmfile.py
rpmrepo.py
storage.py
mkrepo-1.0.2.data/scripts/mkrepo
mkrepo-1.0.2.dist-info/METADATA
mkrepo-1.0.2.dist-info/WHEEL
mkrepo-1.0.2.dist-info/top_level.txt
mkrepo-1.0.2.dist-info/RECORD
