Metadata-Version: 2.1
Name: mkrepo
Version: 1.0.2
Summary: Maintain DEB and RPM repositories on S3
Home-page: https://github.com/tarantool/mkrepo
Author: Konstantin Nazarov
Author-email: mail@kn.am
Keywords: rpm,deb
Classifier: Environment :: Console
Classifier: Intended Audience :: Developers
Classifier: Intended Audience :: System Administrators
Classifier: Operating System :: POSIX
Classifier: Programming Language :: Python :: 3
Classifier: Programming Language :: Python :: 3 :: Only
Classifier: Programming Language :: Python :: 3.6
Classifier: Programming Language :: Python :: 3.7
Classifier: Programming Language :: Python :: 3.8
Classifier: Programming Language :: Python :: 3.9
Classifier: Programming Language :: Python :: 3.10
Classifier: Topic :: System :: Software Distribution
Classifier: Topic :: System :: Systems Administration
Requires-Python: >=3.6.*
Requires-Dist: boto3 (==1.17.5)
Requires-Dist: univers (==30.9.0)
